Workbook

Sheet Supuestos
A1: NERVIK — Revisión DFM (Semana 8) · Equipo 2: Andrik, Juan Pablo, Mauro
A2: Celdas grises = supuestos editables. Todo lo demás son fórmulas. Escenarios: ACTUAL (BOM de la Semana 7), DFM-A (mejoras sin cambiar requisitos del PDS) y DFM-B (DFM-A + cambio de módem, exige renunciar al respaldo 2G del requisito I-04).
A4: Supuesto | B4: Valor | C4: Unidad | D4: Fuente / justificación
A5: Tipo de cambio | B5: 18.65 | C5: MXN/USD | D5: Banxico FIX 27-oct-2026 (igual que Semana 7)
A6: Factor de envío e importación | B6: 0.2 | C6: % de componentes | D6: Supuesto de la Semana 7
A7: Mano de obra | B7: 120 | C7: MXN/h | D7: Supuesto de la Semana 7
A8: Overhead sobre costo directo | B8: 0.15 | C8: % | D8: Método del curso (15%)
A9: Contingencias sobre BOM | B9: 0.25 | C9: % | D9: Método de la Semana 7 (25%)
A10: Ensamble y prueba ACTUAL a 10 u | B10: 25 | C10: min/u | D10: Semana 7 (15 piezas sin contar cinchos; ver hoja Ensamble)
A11: Ensamble y prueba ACTUAL a 100 u | B11: 15 | C11: min/u | D11: Semana 7 (con fixture de pogo pins)
A12: Ensamble y prueba DFM a 10 u | B12: 15 | C12: min/u | D12: Hoja Ensamble: 11 piezas, inserción desde arriba, sin cautín
A13: Ensamble y prueba DFM a 100 u | B13: 10 | C13: min/u | D13: Hoja Ensamble + fixture de pogo pins
A14: Límite de componentes del PDS (C-01) | B14: 650 | C14: MXN a 100 u | D14: PDS v1.0, requisito C-01

Sheet BOM DFM
A1: BOM por escenario — USD por unidad
A2: Precios del 30-oct-2026. Los renglones sin cambio conservan el precio de la Semana 7.
A4: # | B4: Componente | C4: ACTUAL a 10 | D4: ACTUAL a 100 | E4: DFM-A a 10 | F4: DFM-A a 100 | G4: DFM-B a 10 | H4: DFM-B a 100 | I4: Cambio DFM y razón | J4: Estado del precio / fuente
A5: 1 | B5: Microcontrolador RP2040 | C5: 0.993 | D5: 0.7609 | E5: 0.993 | F5: 0.7609 | G5: 0.993 | H5: 0.7609 | I5: Sin cambio: estándar, parte de LCSC. | J5: Verificado (Semana 7)
A6: 2 | B6: Flash W25Q64JV | C6: 0.45 | D6: 0.38 | E6: 0.45 | F6: 0.38 | G6: 0.45 | H6: 0.38 | I6: Sin cambio: parte Basic de JLCPCB. | J6: Estimado (Semana 7)
A7: 3 | B7: Cristal y pasivos del MCU | C7: 0.35 | D7: 0.3 | E7: 0.35 | F7: 0.3 | G7: 0.35 | H7: 0.3 | I7: Sin cambio. | J7: Estimado (Semana 7)
A8: 4 | B8: Controlador CAN MCP2515 | C8: 1.3604 | D8: 1.0467 | E8: 1.3604 | F8: 1.0467 | G8: 1.3604 | H8: 1.0467 | I8: Se conserva: su modo listen-only por registro refuerza el requisito I-02. | J8: Verificado (Semana 7)
A9: 5 | B9: Transceptor CAN aislado ISO1042 | C9: 2.0941 | D9: 1.5976 | E9: 2.0941 | F9: 1.5976 | G9: 2.0941 | H9: 1.5976 | I9: Se conserva: aislamiento y protección de bus de 70 V. | J9: Verificado (Semana 7)
A10: 6 | B10: IMU LSM6DSOX | C10: 1.8766 | D10: 1.6557 | E10: 1.8766 | F10: 1.6557 | G10: 1.8766 | H10: 1.6557 | I10: Sin cambio. | J10: Verificado (Semana 7)
A11: 7 | B11: Módem celular | C11: 25 | D11: 19.91 | E11: 19.91 | F11: 19.11 | G11: 10.93 | H11: 10.5 | I11: A: BG95-M3 comprado a distribuidor autorizado (DigiKey/Avnet) en lugar del estimado de US$25. B: SIMCom SIM7080G (Cat-M/NB-IoT, sin 2G), en existencia en LCSC, montable por JLCPCB. | J11: A: DigiKey US$19.11-19.91 vía Findchips. B: LCSC C2943992 US$10.93 a 10+ (verificado); a 100 estimado
A12: 8 | B12: Receptor GNSS LC76G | C12: 6.29 | D12: 5.48 | E12: 6.29 | F12: 5.48 | G12: 6.29 | H12: 5.48 | I12: Se conserva: el GNSS del módem no opera al mismo tiempo que LTE (multiplexado en tiempo), y la detección continua de C/N0 es el diferenciador. | J12: Verificado (Semana 7); nota de aplicación GNSS de Quectel
A13: 9 | B13: Antenas LTE y GNSS | C13: 4 | D13: 3 | E13: 4 | F13: 3 | G13: 4 | H13: 3 | I13: Sin cambio de costo; la antena GNSS pasa a montaje fijo junto al receptor. | J13: Estimado (Semana 7)
A14: 10 | B14: Etapa de potencia 60 V | C14: 2.2 | D14: 1.6 | E14: 2.2 | F14: 1.6 | G14: 2.2 | H14: 1.6 | I14: Sin cambio. | J14: Estimado (Semana 7)
A15: 11 | B15: Batería LiFePO4 18650 | C15: 4 | D15: 2.5 | E15: 4 | F15: 2.5 | G15: 4 | H15: 2.5 | I15: Celda con lengüetas y conector JST en lugar de portapilas soldado: se conecta sin cautín y se puede reemplazar. | J15: Estimado (Semana 7)
A16: 12 | B16: Cargador LiFePO4 | C16: 0.4 | D16: 0.3 | E16: 0.4 | F16: 0.3 | G16: 0.4 | H16: 0.3 | I16: Sin cambio. | J16: Estimado (Semana 7)
... A18: 14 | B18: Pasivos, conectores y ESD | C18: 2 | D18: 1.5 | E18: 2 | F18: 1.5 | G18: 2 | H18: 1.5 | I18: Pasivos 0402/0603 de valores Basic de JLCPCB. | J18: Estimado (Semana 7)
B19: Subtotal componentes (USD) | C19: =SUM(C5:C18) -> 51.6141 | D19: =SUM(D5:D18) -> 40.4309 | E19: =SUM(E5:E18) -> 46.5241 | F19: =SUM(F5:F18) -> 39.6309 | G19: =SUM(G5:G18) -> 37.5441 | H19: =SUM(H5:H18) -> 31.0209
B20: Subtotal componentes (MXN) | C20: =C19*Supuestos!$B$5 -> 962.60297 | D20: =D19*Supuestos!$B$5 -> 754.03629 | E20: =E19*Supuestos!$B$5 -> 867.67447 | F20: =F19*Supuestos!$B$5 -> 739.11628 | G20: =G19*Supuestos!$B$5 -> 700.19746 | H20: =H19*Supuestos!$B$5 -> 578.53979
B21: Cable J1939 Y Deutsch 9 pines (USD) | C21: 8 | D21: 7.68 | E21: 8 | F21: 7.68 | G21: 8 | H21: 7.68 | I21: Sin cambio: cable estándar comprado, evita arnés propio.
B22: SIM IoT 1NCE 10 años (USD) | C22: 16 | D22: 16 | E22: 16 | F22: 16 | G22: 16 | H22: 16 | I22: No es costo de manufactura: es conectividad prepagada del servicio. Se conserva en el costo del equipo para comparar con la Semana 7.
B23: Envío e importación (MXN) | C23: =(C20+C21*Supuestos!$B$5)*Supuestos!$B$6 -> 222.36059 | D23: =(D20+D21*Supuestos!$B$5)*Supuestos!$B$6 -> 179.45366 | E23: =(E20+E21*Supuestos!$B$5)*Supuestos!$B$6 -> 203.37489 | F23: =(F20+F21*Supuestos!$B$5)*Supuestos!$B$6 -> 176.46966 | G23: =(G20+G21*Supuestos!$B$5)*Supuestos!$B$6 -> 169.87949 | H23: =(H20+H21*Supuestos!$B$5)*Supuestos!$B$6 -> 144.35436
B24: BOM total puesto en México (MXN) | C24: =C20+(C21+C22)*Supuestos!$B$5+C23 -> 1632.5636 | D24: =D20+(D21+D22)*Supuestos!$B$5+D23 -> 1375.1219 | E24: =E20+(E21+E22)*Supuestos!$B$5+E23 -> 1518.6494 | F24: =F20+(F21+F22)*Supuestos!$B$5+F23 -> 1357.2179 | G24: =G20+(G21+G22)*Supuestos!$B$5+G23 -> 1317.677 | H24: =H20+(H21+H22)*Supuestos!$B$5+H23 -> 1164.5261
B25: ¿Cumple C-01 (componentes ≤ $650 a 100 u)? | D25: =IF(D20<=Supuestos!$B$14,"Sí (sobran "&TEXT(Supuestos!$B$14-D20,"$#,##0")&")","No (excede "&TEXT(D20-Supuestos!$B$14,"$#,##0")&")") -> No (excede $104) | F25: =IF(F20<=Supuestos!$B$14,"Sí (sobran "&TEXT(Supuestos!$B$14-F20,"$#,##0")&")","No (excede "&TEXT(F20-Supuestos!$B$14,"$#,##0")&")") -> No (excede $89) | H25: =IF(H20<=Supuestos!$B$14,"Sí (sobran "&TEXT(Supuestos!$B$14-H20,"$#,##0")&")","No (excede "&TEXT(H20-Supuestos!$B$14,"$#,##0")&")") -> Sí (sobran $71)
B26: Peso del módem en los componentes a 100 u | D26: =D11/D19 -> 0.49244513 | F26: =F11/F19 -> 0.4821995 | H26: =H11/H19 -> 0.33848148

Sheet Costo unitario
A1: Costo unitario de manufactura por escenario (MXN)
A3: Concepto | B3: ACTUAL 10 u | C3: ACTUAL 100 u | D3: DFM-A 10 u | E3: DFM-A 100 u | F3: DFM-B 10 u | G3: DFM-B 100 u | H3: Supuesto
A4: BOM total puesto en México | B4: ='BOM DFM'!C24 -> 1632.5636 | C4: ='BOM DFM'!D24 -> 1375.1219 | D4: ='BOM DFM'!E24 -> 1518.6494 | E4: ='BOM DFM'!F24 -> 1357.2179 | F4: ='BOM DFM'!G24 -> 1317.677 | G4: ='BOM DFM'!H24 -> 1164.5261
A5: PCB 4 capas + ensamble SMT (JLCPCB) | B5: 170 | C5: 65 | D5: 170 | E5: 65 | F5: 170 | G5: 65 | H5: Semana 7. En DFM-A el BG95 debe entrar como parte consignada (no está en LCSC); en DFM-B el SIM7080G se monta de catálogo.
A6: Envío de PCBA | B6: 47 | C6: 8 | D6: 47 | E6: 8 | F6: 47 | G6: 8
A7: Carcasa PETG FDM, guías de luz y soporte | B7: 60 | C7: 45 | D7: 60 | E7: 45 | F7: 60 | G7: 45 | H7: Sin cambio de costo: el peine de guías de luz reemplaza 3 piezas por 1 con el mismo material.
A8: Ensamble y prueba | B8: =Supuestos!$B$10/60*Supuestos!$B$7 -> 50 | C8: =Supuestos!$B$11/60*Supuestos!$B$7 -> 30 | D8: =Supuestos!$B$12/60*Supuestos!$B$7 -> 30 | E8: =Supuestos!$B$13/60*Supuestos!$B$7 -> 20 | F8: =Supuestos!$B$12/60*Supuestos!$B$7 -> 30 | G8: =Supuestos!$B$13/60*Supuestos!$B$7 -> 20
A9: Costo directo | B9: =SUM(B4:B8) -> 1959.5636 | C9: =SUM(C4:C8) -> 1523.1219 | D9: =SUM(D4:D8) -> 1825.6494 | E9: =SUM(E4:E8) -> 1495.2179 | F9: =SUM(F4:F8) -> 1624.677 | G9: =SUM(G4:G8) -> 1302.5261
A10: Overhead (15%) | B10: =B9*Supuestos!$B$8 -> 293.93453 | C10: =C9*Supuestos!$B$8 -> 228.46829 | D10: =D9*Supuestos!$B$8 -> 273.8474 | E10: =E9*Supuestos!$B$8 -> 224.28269 | F10: =F9*Supuestos!$B$8 -> 243.70154 | G10: =G9*Supuestos!$B$8 -> 195.37892
A11: Contingencias (25% del BOM) | B11: =B4*Supuestos!$B$9 -> 408.14089 | C11: =C4*Supuestos!$B$9 -> 343.78049 | D11: =D4*Supuestos!$B$9 -> 379.66234 | E11: =E4*Supuestos!$B$9 -> 339.30449 | F11: =F4*Supuestos!$B$9 -> 329.41924 | G11: =G4*Supuestos!$B$9 -> 291.13154
A12: Costo unitario del hardware | B12: =B9+B10+B11 -> 2661.639 | C12: =C9+C10+C11 -> 2095.3707 | D12: =D9+D10+D11 -> 2479.1591 | E12: =E9+E10+E11 -> 2058.8051 | F12: =F9+F10+F11 -> 2197.7977 | G12: =G9+G10+G11 -> 1789.0366
A13: Reducción contra ACTUAL | B13: =B12-B12 -> 0 | C13: =C12-C12 -> 0 | D13: =B12-D12 -> 182.47988 | E13: =C12-E12 -> 36.5656 | F13: =B12-F12 -> 463.84124 | G13: =C12-G12 -> 306.33412
A14: Reducción porcentual | B14: =IF(B12=0,0,B13/B12) -> 0 | C14: =IF(C12=0,0,C13/C12) -> 0 | D14: =IF(B12=0,0,D13/B12) -> 0.068559215 | E14: =IF(C12=0,0,E13/C12) -> 0.017450659 | F14: =IF(B12=0,0,F13/B12) -> 0.17426903 | G14: =IF(C12=0,0,G13/C12) -> 0.14619567
A15: Margen contra precio de venta de $1 800 | B15: =1800-B12 -> -861.63898 | C15: =1800-C12 -> -295.37072 | D15: =1800-D12 -> -679.1591 | E15: =1800-E12 -> -258.80512 | F15: =1800-F12 -> -397.79774 | G15: =1800-G12 -> 10.963401

Sheet Ensamble
A1: Piezas que se manipulan a mano en el ensamble final
A3: Pieza | B3: ACTUAL | C3: DFM | D3: Principio DFA aplicado
A4: Base de la cuña (PETG) | B4: 1 | C4: 1 | D4: Pieza de referencia; se apoya en la mesa sin voltear.
A5: Tapa (PETG) | B5: 1 | C5: 1 | D5: Entra desde arriba; 2 ganchos impresos en el plano XY.
A6: Tornillos autorroscantes | B6: 2 | C6: 2 | D6: Se conservan para abrir y cambiar la batería (reparabilidad).
A7: Guías de luz | B7: 3 | C7: 1 | D7: Peine de 3 guías en una sola pieza: se orienta solo.
A8: Junta de silicón IP54 | B8: 1 | C8: 1 | D8: Cordón en ranura de la base; no requiere orientación.
A9: PCBA | B9: 1 | C9: 1 | D9: Sobre rieles, muesca asimétrica: solo entra en una posición.
A10: Batería 18650 | B10: 1 | C10: 1 | D10: Con lengüetas y conector JST: se conecta sin cautín.
A11: Portapilas soldado | B11: 1 | C11: 0 | D11: Eliminado por la batería con conector.
A12: Antena GNSS con cable | B12: 1 | C12: 0 | D12: Antena cerámica fija junto al receptor, montada por JLCPCB.
A13: Antena LTE flexible | B13: 1 | C13: 1 | D13: Adhesiva en la pared interior, conector U.FL.
A14: Prensaestopa del cable | B14: 1 | C14: 1 | D14: Se conserva por IP54.
A15: Cable J1939 (lado del equipo) | B15: 1 | C15: 1 | D15: Conector con seguro y polarizado.
A16: Cinchos de nailon | B16: 2 | C16: 2 | D16: Los coloca el instalador, no el ensamble.
A17: Total de piezas | B17: =SUM(B4:B16) -> 17 | C17: =SUM(C4:C16) -> 13
A18: Piezas que exigen cautín u orientación manual | B18: 5 | C18: 1 | D18: ACTUAL: portapilas, antena GNSS con cable, 3 guías sueltas. DFM: solo la antena LTE.
